agents_deconstructed/__init__.py
agents_deconstructed/format_tools.py
agents_deconstructed/openai_functions.py
agents_deconstructed/react_chat.py
agents_deconstructed/xml.py
agents_deconstructed-0.0.2.dist-info/METADATA
agents_deconstructed-0.0.2.dist-info/WHEEL
agents_deconstructed-0.0.2.dist-info/top_level.txt
agents_deconstructed-0.0.2.dist-info/RECORD
