Metadata-Version: 2.1
Name: agents-deconstructed
Version: 0.0.2
Summary: Utils for running 'agents' where the core logic is not obfuscated.
Requires-Dist: langchain
